youtube_unofficial/__init__.py
youtube_unofficial/__main__.py
youtube_unofficial/client.py
youtube_unofficial/commands.py
youtube_unofficial/constants.py
youtube_unofficial/download.py
youtube_unofficial/main.py
youtube_unofficial/py.typed
youtube_unofficial/typing/__init__.py
youtube_unofficial/typing/history.py
youtube_unofficial/typing/playlist.py
youtube_unofficial/typing/ytcfg.py
youtube_unofficial/utils.py
youtube_unofficial-0.3.1.dist-info/METADATA
youtube_unofficial-0.3.1.dist-info/WHEEL
youtube_unofficial-0.3.1.dist-info/entry_points.txt
youtube_unofficial-0.3.1.dist-info/licenses/LICENSE.txt
youtube_unofficial-0.3.1.dist-info/RECORD
