Metadata-Version: 2.4
Name: youtube-unofficial
Version: 0.3.1
Summary: Access parts of your account unavailable through normal YouTube API access.
License-Expression: MIT
License-File: LICENSE.txt
Keywords: command line,youtube
Author: Andrew Udvare
Author-email: audvare@gmail.com
Requires-Python: >=3.10,<4.0
Classifier: Development Status :: 4 - Beta
Classifier: Intended Audience :: Developers
Classifier: Programming Language :: Python
Classifier: Programming Language :: Python :: 3.10
Classifier: Programming Language :: Python :: 3.11
Classifier: Programming Language :: Python :: 3.12
Classifier: Programming Language :: Python :: 3.13
Classifier: Programming Language :: Python :: 3.14
Classifier: Typing :: Typed
Requires-Dist: bascom (>=0.1.0,<0.2.0)
Requires-Dist: beautifulsoup4 (>=4.14.3,<5.0.0)
Requires-Dist: click (>=8.3.1,<9.0.0)
Requires-Dist: html5lib (>=1.1,<2.0)
Requires-Dist: more-itertools (>=10.8.0,<11.0.0)
Requires-Dist: requests (>=2.32.5,<3.0.0)
Requires-Dist: typing-extensions (>=4.15.0,<5.0.0)
Requires-Dist: yt-dlp-utils (>=0.0.6,<0.0.7)
Project-URL: Documentation, https://youtube-unofficial.readthedocs.org
Project-URL: Homepage, https://tatsh.github.io/youtube-unofficial/
Project-URL: Issues, https://github.com/Tatsh/youtube-unofficial/issues
Project-URL: Repository, https://github.com/Tatsh/youtube-unofficial
